docker_build/__init__.py
docker_build/__main__.py
docker_build/catalog.py
docker_build/constants.py
docker_build/exception.py
docker_build/logger.py
docker_build/util.py
docker_build/configuration/__init__.py
docker_build/configuration/encoder.py
docker_build/configuration/exception.py
docker_build/configuration/loader.py
docker_build/configuration/model.py
docker_build/configuration/parser.py
docker_build/daemon/__init__.py
docker_build/daemon/catalog.py
docker_build/daemon/exception.py
docker_build/utils/__init__.py
docker_build/utils/argparser.py
docker_build/utils/loader.py
docker_build/utils/logger.py
docker_build_tool-0.13.2.dist-info/DESCRIPTION.rst
docker_build_tool-0.13.2.dist-info/METADATA
docker_build_tool-0.13.2.dist-info/RECORD
docker_build_tool-0.13.2.dist-info/WHEEL
docker_build_tool-0.13.2.dist-info/entry_points.txt
docker_build_tool-0.13.2.dist-info/metadata.json
docker_build_tool-0.13.2.dist-info/top_level.txt
docker_builder/__init__.py
docker_builder/__main__.py
docker_builder/catalog.py
docker_builder/exception.py
docker_builder/util.py
