Metadata-Version: 2.0
Name: docker-build-tool
Version: 0.13.2
Summary: Build tool for creating Docker Images
Home-page: https://github.com/brian-bason/docker-build-tool
Author: Brian Bason
Author-email: brianbason@gmail.com
License: UNKNOWN
Platform: UNKNOWN
Requires-Dist: docker (~=2.0)
Requires-Dist: enum34 (~=1.1)
Requires-Dist: pyYAML (~=3.11)
Provides-Extra: test
Requires-Dist: coverage (==4.0.1); extra == 'test'
Requires-Dist: mock (==1.3.0); extra == 'test'
Requires-Dist: nose (==1.3.7); extra == 'test'
Requires-Dist: testfixtures (==4.3.3); extra == 'test'
